kelp_coverage/__init__.py
kelp_coverage/cli.py
kelp_coverage/heatmap.py
kelp_coverage/pixel_analysis.py
kelp_coverage/sahisam.py
kelp_coverage/segmentation_processors.py
kelp_coverage/tator_download.py
kelp_coverage/visualization.py
kelp_coverage-2.0.1.dist-info/licenses/LICENSE.txt
kelp_coverage-2.0.1.dist-info/METADATA
kelp_coverage-2.0.1.dist-info/WHEEL
kelp_coverage-2.0.1.dist-info/entry_points.txt
kelp_coverage-2.0.1.dist-info/top_level.txt
kelp_coverage-2.0.1.dist-info/RECORD
