Metadata-Version: 2.4
Name: kelp_coverage
Version: 2.0.1
Summary: A tool for calculating kelp coverage from UAV images utilizing Segment Anything Models (SAM)
Author-email: Tim Sananikone <tims3900@gmail.com>
License-Expression: MIT
Project-URL: Homepage, https://github.com/mbari-org/KelpCoverage
Project-URL: Issues, https://github.com/mbari-org/KelpCoverage/issues
Classifier: Programming Language :: Python :: 3
Classifier: Operating System :: OS Independent
Requires-Python: >=3.8
License-File: LICENSE.txt
Requires-Dist: pandas==2.2.2
Requires-Dist: matplotlib==3.10.0
Requires-Dist: shapely==2.1.1
Requires-Dist: numpy==2.0.2
Requires-Dist: torch==2.8.0
Requires-Dist: tqdm==4.67.1
Requires-Dist: segment-anything-py==1.0.1
Requires-Dist: sahi==0.11.34
Requires-Dist: ultralytics==8.3.202
Requires-Dist: opencv-python==4.11.0.86
Requires-Dist: tator==1.5.12
Requires-Dist: urllib3==2.5.0
Requires-Dist: geopandas==1.1.1
Requires-Dist: contextily==1.6.2
Dynamic: license-file
